HISTORY.rst
LICENSE
MANIFEST.in
README.rst
setup.py
wkhtmltox.license
wkhtmltox.tar.gz
bundled_pdfkit.egg-info/PKG-INFO
bundled_pdfkit.egg-info/SOURCES.txt
bundled_pdfkit.egg-info/dependency_links.txt
bundled_pdfkit.egg-info/top_level.txt
pdfkit/__init__.py
pdfkit/api.py
pdfkit/configuration.py
pdfkit/pdfkit.py
pdfkit/source.py