Metadata-Version: 1.1
Name: bundled-pdfkit
Version: 0.6.1
Summary: Wkhtmltopdf python wrapper to convert html to pdf using the webkit rendering engine and qt
Home-page: UNKNOWN
Author: Golovanov Stanislav
Author-email: stgolovanov@gmail.com
License: MIT
Download-URL: https://github.com/mpnowacki/python-pdfkit
Platform: UNKNOWN
Classifier: Programming Language :: Python
Classifier: Programming Language :: Python :: 2.7
Classifier: Programming Language :: Python :: 3.2
Classifier: Programming Language :: Python :: 3.3
Classifier: Topic :: Text Processing
Classifier: Topic :: Text Processing :: General
Classifier: Topic :: Text Processing :: Markup
Classifier: Topic :: Text Processing :: Markup :: HTML
Classifier: Topic :: Text Processing :: Markup :: XML
Classifier: Topic :: Utilities
